[
  {
    "id": "5a7e44fe9e2e",
    "theme": "未分类",
    "signal_groups": [
      "policy_support"
    ],
    "story_score": 36,
    "source_count": 3,
    "sources": [
      "中国政府网-政策",
      "国家发改委-新闻动态",
      "工信部-新闻动态"
    ],
    "top_items": [
      {
        "id": "9efe18553dd10f09",
        "source_id": "gov_cn_policy",
        "source_name": "中国政府网-政策",
        "source_level": "A1",
        "region": "CN",
        "categories": [
          "policy",
          "macro",
          "industry"
        ],
        "title": "国务院关于印发《加快农业农村现代化“十五五”规划》的通知",
        "url": "https://www.gov.cn/zhengce/content/202606/content_7070901.htm",
        "summary": "",
        "published_at": null,
        "fetched_at": "2026-06-05T08:42:12.216705Z",
        "signal_score": 4,
        "risk_score": 0,
        "net_score": 7,
        "signal_hits": {
          "policy_support": [
            "加快",
            "规划"
          ]
        },
        "risk_hits": [],
        "themes": [],
        "evidence_level": "C"
      },
      {
        "id": "0081801b19ac995f",
        "source_id": "gov_cn_policy",
        "source_name": "中国政府网-政策",
        "source_level": "A1",
        "region": "CN",
        "categories": [
          "policy",
          "macro",
          "industry"
        ],
        "title": "国务院关于印发《城市更新“十五五”规划》的通知",
        "url": "https://www.gov.cn/zhengce/content/202605/content_7070539.htm",
        "summary": "",
        "published_at": null,
        "fetched_at": "2026-06-05T08:42:12.216705Z",
        "signal_score": 2,
        "risk_score": 0,
        "net_score": 5,
        "signal_hits": {
          "policy_support": [
            "规划"
          ]
        },
        "risk_hits": [],
        "themes": [],
        "evidence_level": "C"
      },
      {
        "id": "caea21f927942643",
        "source_id": "gov_cn_policy",
        "source_name": "中国政府网-政策",
        "source_level": "A1",
        "region": "CN",
        "categories": [
          "policy",
          "macro",
          "industry"
        ],
        "title": "加快农业农村现代化，“十五五”怎么干",
        "url": "https://www.gov.cn/zhengce/202606/content_7070954.htm",
        "summary": "",
        "published_at": null,
        "fetched_at": "2026-06-05T08:42:12.216705Z",
        "signal_score": 2,
        "risk_score": 0,
        "net_score": 5,
        "signal_hits": {
          "policy_support": [
            "加快"
          ]
        },
        "risk_hits": [],
        "themes": [],
        "evidence_level": "C"
      },
      {
        "id": "f595e1b4e048b0b3",
        "source_id": "gov_cn_policy",
        "source_name": "中国政府网-政策",
        "source_level": "A1",
        "region": "CN",
        "categories": [
          "policy",
          "macro",
          "industry"
        ],
        "title": "国务院5月重要政策",
        "url": "https://www.gov.cn/zhengce/202605/content_7070732.htm",
        "summary": "",
        "published_at": null,
        "fetched_at": "2026-06-05T08:42:12.216705Z",
        "signal_score": 2,
        "risk_score": 0,
        "net_score": 5,
        "signal_hits": {
          "policy_support": [
            "政策"
          ]
        },
        "risk_hits": [],
        "themes": [],
        "evidence_level": "C"
      },
      {
        "id": "55b79b3fa96b6368",
        "source_id": "gov_cn_policy",
        "source_name": "中国政府网-政策",
        "source_level": "A1",
        "region": "CN",
        "categories": [
          "policy",
          "macro",
          "industry"
        ],
        "title": "图表：中央财政下达育儿补贴补助资金999亿元",
        "url": "https://www.gov.cn/zhengce/jiedu/tujie/202606/content_7070900.htm",
        "summary": "",
        "published_at": null,
        "fetched_at": "2026-06-05T08:42:12.216705Z",
        "signal_score": 2,
        "risk_score": 0,
        "net_score": 5,
        "signal_hits": {
          "policy_support": [
            "补贴"
          ]
        },
        "risk_hits": [],
        "themes": [],
        "evidence_level": "C"
      },
      {
        "id": "9debd544c56e8f39",
        "source_id": "ndrc_news",
        "source_name": "国家发改委-新闻动态",
        "source_level": "A1",
        "region": "CN",
        "categories": [
          "policy",
          "macro",
          "industry"
        ],
        "title": "郑栅洁主任主持召开国有企业座谈会 围绕深化国资国企改革及推动国有企业更好服务国家重大战略...",
        "url": "https://www.ndrc.gov.cn/xwdt/xwfb/202606/t20260603_1405679.html",
        "summary": "",
        "published_at": null,
        "fetched_at": "2026-06-05T08:42:12.216705Z",
        "signal_score": 2,
        "risk_score": 0,
        "net_score": 5,
        "signal_hits": {
          "policy_support": [
            "推动"
          ]
        },
        "risk_hits": [],
        "themes": [],
        "evidence_level": "C"
      },
      {
        "id": "18e721d3f9deaa14",
        "source_id": "ndrc_news",
        "source_name": "国家发改委-新闻动态",
        "source_level": "A1",
        "region": "CN",
        "categories": [
          "policy",
          "macro",
          "industry"
        ],
        "title": "关于印发贯彻实施民营经济促进法典型案例(第一批)的通知",
        "url": "https://www.ndrc.gov.cn/xwdt/tzgg/202605/t20260528_1405519.html",
        "summary": "",
        "published_at": null,
        "fetched_at": "2026-06-05T08:42:12.216705Z",
        "signal_score": 2,
        "risk_score": 0,
        "net_score": 5,
        "signal_hits": {
          "policy_support": [
            "促进"
          ]
        },
        "risk_hits": [],
        "themes": [],
        "evidence_level": "C"
      },
      {
        "id": "4930a69697394106",
        "source_id": "ndrc_news",
        "source_name": "国家发改委-新闻动态",
        "source_level": "A1",
        "region": "CN",
        "categories": [
          "policy",
          "macro",
          "industry"
        ],
        "title": "郑栅洁主任主持召开国有企业座谈会 围绕深化国资国企改革及推动国有企业更好服务国家重大战略...",
        "url": "https://www.ndrc.gov.cn/fzggw/wld/zsj/zyhd/202606/t20260603_1405672.html",
        "summary": "",
        "published_at": null,
        "fetched_at": "2026-06-05T08:42:12.216705Z",
        "signal_score": 2,
        "risk_score": 0,
        "net_score": 5,
        "signal_hits": {
          "policy_support": [
            "推动"
          ]
        },
        "risk_hits": [],
        "themes": [],
        "evidence_level": "C"
      }
    ],
    "risk_flags": []
  },
  {
    "id": "aaa61abb23b9",
    "theme": "未分类",
    "signal_groups": [
      "demand_strong"
    ],
    "story_score": 11,
    "source_count": 1,
    "sources": [
      "国家统计局-数据发布"
    ],
    "top_items": [
      {
        "id": "1a5de1c0fbf6987b",
        "source_id": "stats_cn",
        "source_name": "国家统计局-数据发布",
        "source_level": "A1",
        "region": "CN",
        "categories": [
          "macro",
          "industry"
        ],
        "title": "2026年5月中国采购经理指数运行情况",
        "url": "https://www.stats.gov.cn/sj/zxfb/202605/t20260531_1963824.html",
        "summary": "",
        "published_at": null,
        "fetched_at": "2026-06-05T08:42:12.216705Z",
        "signal_score": 5,
        "risk_score": 0,
        "net_score": 8,
        "signal_hits": {
          "demand_strong": [
            "采购"
          ]
        },
        "risk_hits": [],
        "themes": [],
        "evidence_level": "C"
      }
    ],
    "risk_flags": []
  },
  {
    "id": "ee3293e50c9c",
    "theme": "消费出海",
    "signal_groups": [
      "policy_support"
    ],
    "story_score": 8,
    "source_count": 1,
    "sources": [
      "国家发改委-新闻动态"
    ],
    "top_items": [
      {
        "id": "2ca153d20934db44",
        "source_id": "ndrc_news",
        "source_name": "国家发改委-新闻动态",
        "source_level": "A1",
        "region": "CN",
        "categories": [
          "policy",
          "macro",
          "industry"
        ],
        "title": "推动大规模设备更新和消费品以旧换新",
        "url": "https://www.ndrc.gov.cn/xwdt/ztzl/tddgmsbgxhxfpyjhx/",
        "summary": "",
        "published_at": null,
        "fetched_at": "2026-06-05T08:42:12.216705Z",
        "signal_score": 2,
        "risk_score": 0,
        "net_score": 5,
        "signal_hits": {
          "policy_support": [
            "推动"
          ]
        },
        "risk_hits": [],
        "themes": [
          "消费出海"
        ],
        "evidence_level": "C"
      }
    ],
    "risk_flags": []
  }
]